colored/__init__.py
colored/attributes.py
colored/background.py
colored/colored.py
colored/controls.py
colored/cprint.py
colored/exceptions.py
colored/foreground.py
colored/hexadecimal.py
colored/library.py
colored/utilities.py
colored-2.2.2.dist-info/WHEEL
colored-2.2.2.dist-info/METADATA
colored-2.2.2.dist-info/RECORD
