Metadata-Version: 2.1
Name: colored
Version: 2.2.2
Summary: Simple python library for color and formatting to terminal
Keywords: xterm,color,colour,vt100,ansi,terminal,text,rgb,linux,windows
Author-email: Dimitris Zlatanidis <dslackw@gmail.com>
Requires-Python: >=3.9
Classifier: Development Status :: 5 - Production/Stable
Classifier: Environment :: Console
Classifier: License :: OSI Approved :: MIT License
Classifier: Operating System :: POSIX :: Other
Classifier: Operating System :: POSIX :: Linux
Classifier: Operating System :: Microsoft :: Windows
Classifier: Operating System :: Microsoft :: Windows :: Windows 10
Classifier: Operating System :: OS Independent
Classifier: Programming Language :: Python :: 3
Classifier: Topic :: Terminals
Project-URL: homepage, https://dslackw.gitlab.io/colored/
